genepass/__init__.py
genepass/genepass.py
genepass-0.1.6.dist-info/LICENSE
genepass-0.1.6.dist-info/METADATA
genepass-0.1.6.dist-info/WHEEL
genepass-0.1.6.dist-info/top_level.txt
genepass-0.1.6.dist-info/RECORD
