Metadata-Version: 2.1
Name: genepass
Version: 0.1.6
Summary: genepass can automatically generate (create) passwords
Home-page: https://github.com/senya-koku/genepass
Author: ny7777
Author-email: 5938dai617@gmail.com
License: MIT
License-File: LICENSE
